lcwc/__init__.py
lcwc/category.py
lcwc/client.py
lcwc/incident.py
lcwc/unit.py
lcwc/agencies/__init__.py
lcwc/agencies/agency.py
lcwc/agencies/agencyclient.py
lcwc/agencies/agencyresolver.py
lcwc/agencies/exceptions.py
lcwc/arcgis/__init__.py
lcwc/arcgis/client.py
lcwc/arcgis/incident.py
lcwc/feed/__init__.py
lcwc/feed/client.py
lcwc/feed/incident.py
lcwc/feed/parser.py
lcwc/feed/utils/__init__.py
lcwc/utils/__init__.py
lcwc/utils/encoding.py
lcwc/utils/restadapter.py
lcwc/utils/unitconverter.py
lcwc/utils/unitparser.py
lcwc/web/__init__.py
lcwc/web/client.py
lcwc/web/incident.py
lcwc/web/parser.py
lcwc-0.12.3.dist-info/LICENSE
lcwc-0.12.3.dist-info/METADATA
lcwc-0.12.3.dist-info/WHEEL
lcwc-0.12.3.dist-info/top_level.txt
lcwc-0.12.3.dist-info/RECORD
