Metadata-Version: 2.1
Name: lcwc
Version: 0.12.3
Summary: Python library for fetching the Lancaster County-Wide Communications live incident list.
Author-email: Nate Shoffner <nate.shoffner@gmail.com>
Project-URL: Homepage, https://github.com/NateShoffner/python-lcwc
Project-URL: Bug Tracker, https://github.com/NateShoffner/python-lcwc/issues
Keywords: lcwc,lancaster,police,fire,ems,dispatch,911,incident
Classifier: Programming Language :: Python :: 3
Classifier: License :: OSI Approved :: MIT License
Classifier: Operating System :: OS Independent
Requires-Python: >=3.9
License-File: LICENSE
Requires-Dist: bs4
Requires-Dist: aiohttp
Requires-Dist: feedparser
Requires-Dist: pytz
